MANIFEST.in
README.rst
requirements.txt
setup.py
django_sympa.egg-info/PKG-INFO
django_sympa.egg-info/SOURCES.txt
django_sympa.egg-info/dependency_links.txt
django_sympa.egg-info/top_level.txt
sympa/__init__.py
sympa/views.py
sympa/templates/users.sympa
tests/__init__.py
tests/models.py
tests/tests.py
tests/urls.py