Metadata-Version: 1.1
Name: django-sympa
Version: 0.1.1
Summary: Add a view to interact with sympa
Home-page: https://github.com/unistra/django-sympa/
Author: di-dip-unistra
Author-email: di-dip@unistra.fr
License: PSF
Keywords: django,Université de Strasbourg,sympa,mail,users
Platform: UNKNOWN
Classifier: Development Status :: 4 - Beta
Classifier: Environment :: Web Environment
Classifier: Framework :: Django :: 1.4
Classifier: Framework :: Django :: 1.5
Classifier: Framework :: Django :: 1.6
Classifier: Framework :: Django :: 1.7
Classifier: Intended Audience :: Developers
Classifier: License :: OSI Approved :: GNU General Public License v2 (GPLv2)
Classifier: Programming Language :: Python :: 2.7
Classifier: Programming Language :: Python :: 3.4
Classifier: Topic :: Communications :: Email :: Mailing List Servers
